Workbook

Sheet 说明
A1: 猕猴桃采后GA₃处理分析与应用测算底稿
A2: 用于试验数据复核、经营数据对账、情景测算、证据边界和决策门槛管理。蓝色表头为结构字段；浅黄色单元格为可调整情景假设。
A4: 项目 | B4: 说明
A5: 工作簿用途 | B5: 为管理报告提供可复算的数据、公式和证据索引；不替代原始附件。
A6: 数据优先级 | B6: 原始工作簿与逐笔经营记录 > 材料目录与口径说明 > 公开证据摘要。
A7: 试验边界 | B7: 现有工作簿未记录品种、产地、处理浓度、施用方式、温湿度和重复独立性，相关条件不得补写为本项目事实。
A8: 经营边界 | B8: 经营数据为业务测算样例，不代表GA₃已实施或收益已实现。
A9: 统计口径 | B9: 均值与样本标准差按每组每时点三条记录计算；Welch双侧t检验和30次Bonferroni校正仅作探索性参考。
A10: 合规边界 | B10: 商品化应用须另行核对具体产品的有效登记、核准标签、使用范围与方法及适用残留要求。
A11: 工作表结构 | B11: 试验原始数据—试验统计—业务原始表—批次对账—经营基线—情景测算—证据台账—决策门槛。

Sheet 试验原始数据
A1: 试验原始数据
A2: 逐条保留六份指标工作簿中的记录；单位单列，不改写原始测定值。
A4: 指标 | B4: 单位 | C4: 时间(d) | D4: 处理 | E4: 重复 | F4: 测定值 | G4: 来源文件
A5: 硬度 | B5: N | C5: 0 | D5: CK | E5: 1 | F5: 84.2 | G5: 实验资料/硬度.xlsx
A6: 硬度 | B6: N | C6: 0 | D6: CK | E6: 2 | F6: 83.8 | G6: 实验资料/硬度.xlsx
A7: 硬度 | B7: N | C7: 0 | D7: CK | E7: 3 | F7: 84.5 | G7: 实验资料/硬度.xlsx
A8: 硬度 | B8: N | C8: 0 | D8: GA3 | E8: 1 | F8: 84.1 | G8: 实验资料/硬度.xlsx
A9: 硬度 | B9: N | C9: 0 | D9: GA3 | E9: 2 | F9: 84 | G9: 实验资料/硬度.xlsx
A10: 硬度 | B10: N | C10: 0 | D10: GA3 | E10: 3 | F10: 83.9 | G10: 实验资料/硬度.xlsx
A11: 硬度 | B11: N | C11: 7 | D11: CK | E11: 1 | F11: 61.5 | G11: 实验资料/硬度.xlsx
A12: 硬度 | B12: N | C12: 7 | D12: CK | E12: 2 | F12: 58 | G12: 实验资料/硬度.xlsx
A13: 硬度 | B13: N | C13: 7 | D13: CK | E13: 3 | F13: 60.5 | G13: 实验资料/硬度.xlsx
A14: 硬度 | B14: N | C14: 7 | D14: GA3 | E14: 1 | F14: 76.5 | G14: 实验资料/硬度.xlsx
A15: 硬度 | B15: N | C15: 7 | D15: GA3 | E15: 2 | F15: 73.5 | G15: 实验资料/硬度.xlsx
A16: 硬度 | B16: N | C16: 7 | D16: GA3 | E16: 3 | F16: 75 | G16: 实验资料/硬度.xlsx
... A184: 抗坏血酸 | B184: g·kg⁻¹ FW | C184: 28 | D184: GA3 | E184: 3 | F184: 0.5 | G184: 实验资料/抗坏血酸.xlsx

Sheet 试验统计
A1: 试验统计
A2: 均值、样本标准差、组间差异和探索性检验均由“试验原始数据”公式联动；p值不替代效应量、轨迹和独立批次复现。
A4: 指标 | B4: 单位 | C4: 时间(d) | D4: CK均值 | E4: CK样本SD | F4: GA3均值 | G4: GA3样本SD | H4: 差值(GA3-CK) | I4: 相对差异 | J4: Welch双侧p | K4: Bonferroni p | L4: 方向 | M4: 原始数据行 | O4: 时间(d) | P4: CK硬度(N) | Q4: GA3硬度(N)
A5: 硬度 | B5: N | C5: 0 | D5: =AVERAGE('试验原始数据'!$F$5:$F$7) | E5: =STDEV.S('试验原始数据'!$F$5:$F$7) | F5: =AVERAGE('试验原始数据'!$F$8:$F$10) | G5: =STDEV.S('试验原始数据'!$F$8:$F$10) | H5: =F5-D5 | I5: =IF(D5=0,"",H5/ABS(D5)) | J5: =IF(AND(E5=0,G5=0),IF(H5=0,1,""),T.TEST('试验原始数据'!$F$5:$F$7,'试验原始数据'!$F$8:$F$10,2,3)) | K5: =IF(J5="","",MIN(1,J5*30)) | L5: =IF(H5>0,"GA₃高于CK",IF(H5<0,"GA₃低于CK","无差异")) | M5: ="试验原始数据!"&"F5:F10" | O5: =C5 | P5: =D5 | Q5: =F5
A6: 硬度 | B6: N | C6: 7 | D6: =AVERAGE('试验原始数据'!$F$11:$F$13) | E6: =STDEV.S('试验原始数据'!$F$11:$F$13) | F6: =AVERAGE('试验原始数据'!$F$14:$F$16) | G6: =STDEV.S('试验原始数据'!$F$14:$F$16) | H6: =F6-D6 | I6: =IF(D6=0,"",H6/ABS(D6)) | J6: =IF(AND(E6=0,G6=0),IF(H6=0,1,""),T.TEST('试验原始数据'!$F$11:$F$13,'试验原始数据'!$F$14:$F$16,2,3)) | K6: =IF(J6="","",MIN(1,J6*30)) | L6: =IF(H6>0,"GA₃高于CK",IF(H6<0,"GA₃低于CK","无差异")) | M6: ="试验原始数据!"&"F11:F16" | O6: =C6 | P6: =D6 | Q6: =F6
A7: 硬度 | B7: N | C7: 14 | D7: =AVERAGE('试验原始数据'!$F$17:$F$19) | E7: =STDEV.S('试验原始数据'!$F$17:$F$19) | F7: =AVERAGE('试验原始数据'!$F$20:$F$22) | G7: =STDEV.S('试验原始数据'!$F$20:$F$22) | H7: =F7-D7 | I7: =IF(D7=0,"",H7/ABS(D7)) | J7: =IF(AND(E7=0,G7=0),IF(H7=0,1,""),T.TEST('试验原始数据'!$F$17:$F$19,'试验原始数据'!$F$20:$F$22,2,3)) | K7: =IF(J7="","",MIN(1,J7*30)) | L7: =IF(H7>0,"GA₃高于CK",IF(H7<0,"GA₃低于CK","无差异")) | M7: ="试验原始数据!"&"F17:F22" | O7: =C7 | P7: =D7 | Q7: =F7
A8: 硬度 | B8: N | C8: 21 | D8: =AVERAGE('试验原始数据'!$F$23:$F$25) | E8: =STDEV.S('试验原始数据'!$F$23:$F$25) | F8: =AVERAGE('试验原始数据'!$F$26:$F$28) | G8: =STDEV.S('试验原始数据'!$F$26:$F$28) | H8: =F8-D8 | I8: =IF(D8=0,"",H8/ABS(D8)) | J8: =IF(AND(E8=0,G8=0),IF(H8=0,1,""),T.TEST('试验原始数据'!$F$23:$F$25,'试验原始数据'!$F$26:$F$28,2,3)) | K8: =IF(J8="","",MIN(1,J8*30)) | L8: =IF(H8>0,"GA₃高于CK",IF(H8<0,"GA₃低于CK","无差异")) | M8: ="试验原始数据!"&"F23:F28" | O8: =C8 | P8: =D8 | Q8: =F8
A9: 硬度 | B9: N | C9: 28 | D9: =AVERAGE('试验原始数据'!$F$29:$F$31) | E9: =STDEV.S('试验原始数据'!$F$29:$F$31) | F9: =AVERAGE('试验原始数据'!$F$32:$F$34) | G9: =STDEV.S('试验原始数据'!$F$32:$F$34) | H9: =F9-D9 | I9: =IF(D9=0,"",H9/ABS(D9)) | J9: =IF(AND(E9=0,G9=0),IF(H9=0,1,""),T.TEST('试验原始数据'!$F$29:$F$31,'试验原始数据'!$F$32:$F$34,2,3)) | K9: =IF(J9="","",MIN(1,J9*30)) | L9: =IF(H9>0,"GA₃高于CK",IF(H9<0,"GA₃低于CK","无差异")) | M9: ="试验原始数据!"&"F29:F34" | O9: =C9 | P9: =D9 | Q9: =F9
A10: 可溶性固形物 | B10: % | C10: 0 | D10: =AVERAGE('试验原始数据'!$F$35:$F$37) | E10: =STDEV.S('试验原始数据'!$F$35:$F$37) | F10: =AVERAGE('试验原始数据'!$F$38:$F$40) | G10: =STDEV.S('试验原始数据'!$F$38:$F$40) | H10: =F10-D10 | I10: =IF(D10=0,"",H10/ABS(D10)) | J10: =IF(AND(E10=0,G10=0),IF(H10=0,1,""),T.TEST('试验原始数据'!$F$35:$F$37,'试验原始数据'!$F$38:$F$40,2,3)) | K10: =IF(J10="","",MIN(1,J10*30)) | L10: =IF(H10>0,"GA₃高于CK",IF(H10<0,"GA₃低于CK","无差异")) | M10: ="试验原始数据!"&"F35:F40"
A11: 可溶性固形物 | B11: % | C11: 7 | D11: =AVERAGE('试验原始数据'!$F$41:$F$43) | E11: =STDEV.S('试验原始数据'!$F$41:$F$43) | F11: =AVERAGE('试验原始数据'!$F$44:$F$46) | G11: =STDEV.S('试验原始数据'!$F$44:$F$46) | H11: =F11-D11 | I11: =IF(D11=0,"",H11/ABS(D11)) | J11: =IF(AND(E11=0,G11=0),IF(H11=0,1,""),T.TEST('试验原始数据'!$F$41:$F$43,'试验原始数据'!$F$44:$F$46,2,3)) | K11: =IF(J11="","",MIN(1,J11*30)) | L11: =IF(H11>0,"GA₃高于CK",IF(H11<0,"GA₃低于CK","无差异")) | M11: ="试验原始数据!"&"F41:F46"
A12: 可溶性固形物 | B12: % | C12: 14 | D12: =AVERAGE('试验原始数据'!$F$47:$F$49) | E12: =STDEV.S('试验原始数据'!$F$47:$F$49) | F12: =AVERAGE('试验原始数据'!$F$50:$F$52) | G12: =STDEV.S('试验原始数据'!$F$50:$F$52) | H12: =F12-D12 | I12: =IF(D12=0,"",H12/ABS(D12)) | J12: =IF(AND(E12=0,G12=0),IF(H12=0,1,""),T.TEST('试验原始数据'!$F$47:$F$49,'试验原始数据'!$F$50:$F$52,2,3)) | K12: =IF(J12="","",MIN(1,J12*30)) | L12: =IF(H12>0,"GA₃高于CK",IF(H12<0,"GA₃低于CK","无差异")) | M12: ="试验原始数据!"&"F47:F52"
A13: 可溶性固形物 | B13: % | C13: 21 | D13: =AVERAGE('试验原始数据'!$F$53:$F$55) | E13: =STDEV.S('试验原始数据'!$F$53:$F$55) | F13: =AVERAGE('试验原始数据'!$F$56:$F$58) | G13: =STDEV.S('试验原始数据'!$F$56:$F$58) | H13: =F13-D13 | I13: =IF(D13=0,"",H13/ABS(D13)) | J13: =IF(AND(E13=0,G13=0),IF(H13=0,1,""),T.TEST('试验原始数据'!$F$53:$F$55,'试验原始数据'!$F$56:$F$58,2,3)) | K13: =IF(J13="","",MIN(1,J13*30)) | L13: =IF(H13>0,"GA₃高于CK",IF(H13<0,"GA₃低于CK","无差异")) | M13: ="试验原始数据!"&"F53:F58"
A14: 可溶性固形物 | B14: % | C14: 28 | D14: =AVERAGE('试验原始数据'!$F$59:$F$61) | E14: =STDEV.S('试验原始数据'!$F$59:$F$61) | F14: =AVERAGE('试验原始数据'!$F$62:$F$64) | G14: =STDEV.S('试验原始数据'!$F$62:$F$64) | H14: =F14-D14 | I14: =IF(D14=0,"",H14/ABS(D14)) | J14: =IF(AND(E14=0,G14=0),IF(H14=0,1,""),T.TEST('试验原始数据'!$F$59:$F$61,'试验原始数据'!$F$62:$F$64,2,3)) | K14: =IF(J14="","",MIN(1,J14*30)) | L14: =IF(H14>0,"GA₃高于CK",IF(H14<0,"GA₃低于CK","无差异")) | M14: ="试验原始数据!"&"F59:F64"
A15: 总酸 | B15: % | C15: 0 | D15: =AVERAGE('试验原始数据'!$F$65:$F$67) | E15: =STDEV.S('试验原始数据'!$F$65:$F$67) | F15: =AVERAGE('试验原始数据'!$F$68:$F$70) | G15: =STDEV.S('试验原始数据'!$F$68:$F$70) | H15: =F15-D15 | I15: =IF(D15=0,"",H15/ABS(D15)) | J15: =IF(AND(E15=0,G15=0),IF(H15=0,1,""),T.TEST('试验原始数据'!$F$65:$F$67,'试验原始数据'!$F$68:$F$70,2,3)) | K15: =IF(J15="","",MIN(1,J15*30)) | L15: =IF(H15>0,"GA₃高于CK",IF(H15<0,"GA₃低于CK","无差异")) | M15: ="试验原始数据!"&"F65:F70"
A16: 总酸 | B16: % | C16: 7 | D16: =AVERAGE('试验原始数据'!$F$71:$F$73) | E16: =STDEV.S('试验原始数据'!$F$71:$F$73) | F16: =AVERAGE('试验原始数据'!$F$74:$F$76) | G16: =STDEV.S('试验原始数据'!$F$74:$F$76) | H16: =F16-D16 | I16: =IF(D16=0,"",H16/ABS(D16)) | J16: =IF(AND(E16=0,G16=0),IF(H16=0,1,""),T.TEST('试验原始数据'!$F$71:$F$73,'试验原始数据'!$F$74:$F$76,2,3)) | K16: =IF(J16="","",MIN(1,J16*30)) | L16: =IF(H16>0,"GA₃高于CK",IF(H16<0,"GA₃低于CK","无差异")) | M16: ="试验原始数据!"&"F71:F76"
A17: 总酸 | B17: % | C17: 14 | D17: =AVERAGE('试验原始数据'!$F$77:$F$79) | E17: =STDEV.S('试验原始数据'!$F$77:$F$79) | F17: =AVERAGE('试验原始数据'!$F$80:$F$82) | G17: =STDEV.S('试验原始数据'!$F$80:$F$82) | H17: =F17-D17 | I17: =IF(D17=0,"",H17/ABS(D17)) | J17: =IF(AND(E17=0,G17=0),IF(H17=0,1,""),T.TEST('试验原始数据'!$F$77:$F$79,'试验原始数据'!$F$80:$F$82,2,3)) | K17: =IF(J17="","",MIN(1,J17*30)) | L17: =IF(H17>0,"GA₃高于CK",IF(H17<0,"GA₃低于CK","无差异")) | M17: ="试验原始数据!"&"F77:F82"
A18: 总酸 | B18: % | C18: 21 | D18: =AVERAGE('试验原始数据'!$F$83:$F$85) | E18: =STDEV.S('试验原始数据'!$F$83:$F$85) | F18: =AVERAGE('试验原始数据'!$F$86:$F$88) | G18: =STDEV.S('试验原始数据'!$F$86:$F$88) | H18: =F18-D18 | I18: =IF(D18=0,"",H18/ABS(D18)) | J18: =IF(AND(E18=0,G18=0),IF(H18=0,1,""),T.TEST('试验原始数据'!$F$83:$F$85,'试验原始数据'!$F$86:$F$88,2,3)) | K18: =IF(J18="","",MIN(1,J18*30)) | L18: =IF(H18>0,"GA₃高于CK",IF(H18<0,"GA₃低于CK","无差异")) | M18: ="试验原始数据!"&"F83:F88"
A19: 总酸 | B19: % | C19: 28 | D19: =AVERAGE('试验原始数据'!$F$89:$F$91) | E19: =STDEV.S('试验原始数据'!$F$89:$F$91) | F19: =AVERAGE('试验原始数据'!$F$92:$F$94) | G19: =STDEV.S('试验原始数据'!$F$92:$F$94) | H19: =F19-D19 | I19: =IF(D19=0,"",H19/ABS(D19)) | J19: =IF(AND(E19=0,G19=0),IF(H19=0,1,""),T.TEST('试验原始数据'!$F$89:$F$91,'试验原始数据'!$F$92:$F$94,2,3)) | K19: =IF(J19="","",MIN(1,J19*30)) | L19: =IF(H19>0,"GA₃高于CK",IF(H19<0,"GA₃低于CK","无差异")) | M19: ="试验原始数据!"&"F89:F94"
A20: 乙烯释放速率 | B20: μL·kg⁻¹·h⁻¹ | C20: 0 | D20: =AVERAGE('试验原始数据'!$F$95:$F$97) | E20: =STDEV.S('试验原始数据'!$F$95:$F$97) | F20: =AVERAGE('试验原始数据'!$F$98:$F$100) | G20: =STDEV.S('试验原始数据'!$F$98:$F$100) | H20: =F20-D20 | I20: =IF(D20=0,"",H20/ABS(D20)) | J20: =IF(AND(E20=0,G20=0),IF(H20=0,1,""),T.TEST('试验原始数据'!$F$95:$F$97,'试验原始数据'!$F$98:$F$100,2,3)) | K20: =IF(J20="","",MIN(1,J20*30)) | L20: =IF(H20>0,"GA₃高于CK",IF(H20<0,"GA₃低于CK","无差异")) | M20: ="试验原始数据!"&"F95:F100"
A21: 乙烯释放速率 | B21: μL·kg⁻¹·h⁻¹ | C21: 7 | D21: =AVERAGE('试验原始数据'!$F$101:$F$103) | E21: =STDEV.S('试验原始数据'!$F$101:$F$103) | F21: =AVERAGE('试验原始数据'!$F$104:$F$106) | G21: =STDEV.S('试验原始数据'!$F$104:$F$106) | H21: =F21-D21 | I21: =IF(D21=0,"",H21/ABS(D21)) | J21: =IF(AND(E21=0,G21=0),IF(H21=0,1,""),T.TEST('试验原始数据'!$F$101:$F$103,'试验原始数据'!$F$104:$F$106,2,3)) | K21: =IF(J21="","",MIN(1,J21*30)) | L21: =IF(H21>0,"GA₃高于CK",IF(H21<0,"GA₃低于CK","无差异")) | M21: ="试验原始数据!"&"F101:F106"
A22: 乙烯释放速率 | B22: μL·kg⁻¹·h⁻¹ | C22: 14 | D22: =AVERAGE('试验原始数据'!$F$107:$F$109) | E22: =STDEV.S('试验原始数据'!$F$107:$F$109) | F22: =AVERAGE('试验原始数据'!$F$110:$F$112) | G22: =STDEV.S('试验原始数据'!$F$110:$F$112) | H22: =F22-D22 | I22: =IF(D22=0,"",H22/ABS(D22)) | J22: =IF(AND(E22=0,G22=0),IF(H22=0,1,""),T.TEST('试验原始数据'!$F$107:$F$109,'试验原始数据'!$F$110:$F$112,2,3)) | K22: =IF(J22="","",MIN(1,J22*30)) | L22: =IF(H22>0,"GA₃高于CK",IF(H22<0,"GA₃低于CK","无差异")) | M22: ="试验原始数据!"&"F107:F112"
A23: 乙烯释放速率 | B23: μL·kg⁻¹·h⁻¹ | C23: 21 | D23: =AVERAGE('试验原始数据'!$F$113:$F$115) | E23: =STDEV.S('试验原始数据'!$F$113:$F$115) | F23: =AVERAGE('试验原始数据'!$F$116:$F$118) | G23: =STDEV.S('试验原始数据'!$F$116:$F$118) | H23: =F23-D23 | I23: =IF(D23=0,"",H23/ABS(D23)) | J23: =IF(AND(E23=0,G23=0),IF(H23=0,1,""),T.TEST('试验原始数据'!$F$113:$F$115,'试验原始数据'!$F$116:$F$118,2,3)) | K23: =IF(J23="","",MIN(1,J23*30)) | L23: =IF(H23>0,"GA₃高于CK",IF(H23<0,"GA₃低于CK","无差异")) | M23: ="试验原始数据!"&"F113:F118"
A24: 乙烯释放速率 | B24: μL·kg⁻¹·h⁻¹ | C24: 28 | D24: =AVERAGE('试验原始数据'!$F$119:$F$121) | E24: =STDEV.S('试验原始数据'!$F$119:$F$121) | F24: =AVERAGE('试验原始数据'!$F$122:$F$124) | G24: =STDEV.S('试验原始数据'!$F$122:$F$124) | H24: =F24-D24 | I24: =IF(D24=0,"",H24/ABS(D24)) | J24: =IF(AND(E24=0,G24=0),IF(H24=0,1,""),T.TEST('试验原始数据'!$F$119:$F$121,'试验原始数据'!$F$122:$F$124,2,3)) | K24: =IF(J24="","",MIN(1,J24*30)) | L24: =IF(H24>0,"GA₃高于CK",IF(H24<0,"GA₃低于CK","无差异")) | M24: ="试验原始数据!"&"F119:F124"
A25: 淀粉含量 | B25: g·kg⁻¹ FW | C25: 0 | D25: =AVERAGE('试验原始数据'!$F$125:$F$127) | E25: =STDEV.S('试验原始数据'!$F$125:$F$127) | F25: =AVERAGE('试验原始数据'!$F$128:$F$130) | G25: =STDEV.S('试验原始数据'!$F$128:$F$130) | H25: =F25-D25 | I25: =IF(D25=0,"",H25/ABS(D25)) | J25: =IF(AND(E25=0,G25=0),IF(H25=0,1,""),T.TEST('试验原始数据'!$F$125:$F$127,'试验原始数据'!$F$128:$F$130,2,3)) | K25: =IF(J25="","",MIN(1,J25*30)) | L25: =IF(H25>0,"GA₃高于CK",IF(H25<0,"GA₃低于CK","无差异")) | M25: ="试验原始数据!"&"F125:F130"
A26: 淀粉含量 | B26: g·kg⁻¹ FW | C26: 7 | D26: =AVERAGE('试验原始数据'!$F$131:$F$133) | E26: =STDEV.S('试验原始数据'!$F$131:$F$133) | F26: =AVERAGE('试验原始数据'!$F$134:$F$136) | G26: =STDEV.S('试验原始数据'!$F$134:$F$136) | H26: =F26-D26 | I26: =IF(D26=0,"",H26/ABS(D26)) | J26: =IF(AND(E26=0,G26=0),IF(H26=0,1,""),T.TEST('试验原始数据'!$F$131:$F$133,'试验原始数据'!$F$134:$F$136,2,3)) | K26: =IF(J26="","",MIN(1,J26*30)) | L26: =IF(H26>0,"GA₃高于CK",IF(H26<0,"GA₃低于CK","无差异")) | M26: ="试验原始数据!"&"F131:F136"
A27: 淀粉含量 | B27: g·kg⁻¹ FW | C27: 14 | D27: =AVERAGE('试验原始数据'!$F$137:$F$139) | E27: =STDEV.S('试验原始数据'!$F$137:$F$139) | F27: =AVERAGE('试验原始数据'!$F$140:$F$142) | G27: =STDEV.S('试验原始数据'!$F$140:$F$142) | H27: =F27-D27 | I27: =IF(D27=0,"",H27/ABS(D27)) | J27: =IF(AND(E27=0,G27=0),IF(H27=0,1,""),T.TEST('试验原始数据'!$F$137:$F$139,'试验原始数据'!$F$140:$F$142,2,3)) | K27: =IF(J27="","",MIN(1,J27*30)) | L27: =IF(H27>0,"GA₃高于CK",IF(H27<0,"GA₃低于CK","无差异")) | M27: ="试验原始数据!"&"F137:F142"
A28: 淀粉含量 | B28: g·kg⁻¹ FW | C28: 21 | D28: =AVERAGE('试验原始数据'!$F$143:$F$145) | E28: =STDEV.S('试验原始数据'!$F$143:$F$145) | F28: =AVERAGE('试验原始数据'!$F$146:$F$148) | G28: =STDEV.S('试验原始数据'!$F$146:$F$148) | H28: =F28-D28 | I28: =IF(D28=0,"",H28/ABS(D28)) | J28: =IF(AND(E28=0,G28=0),IF(H28=0,1,""),T.TEST('试验原始数据'!$F$143:$F$145,'试验原始数据'!$F$146:$F$148,2,3)) | K28: =IF(J28="","",MIN(1,J28*30)) | L28: =IF(H28>0,"GA₃高于CK",IF(H28<0,"GA₃低于CK","无差异")) | M28: ="试验原始数据!"&"F143:F148"
A29: 淀粉含量 | B29: g·kg⁻¹ FW | C29: 28 | D29: =AVERAGE('试验原始数据'!$F$149:$F$151) | E29: =STDEV.S('试验原始数据'!$F$149:$F$151) | F29: =AVERAGE('试验原始数据'!$F$152:$F$154) | G29: =STDEV.S('试验原始数据'!$F$152:$F$154) | H29: =F29-D29 | I29: =IF(D29=0,"",H29/ABS(D29)) | J29: =IF(AND(E29=0,G29=0),IF(H29=0,1,""),T.TEST('试验原始数据'!$F$149:$F$151,'试验原始数据'!$F$152:$F$154,2,3)) | K29: =IF(J29="","",MIN(1,J29*30)) | L29: =IF(H29>0,"GA₃高于CK",IF(H29<0,"GA₃低于CK","无差异")) | M29: ="试验原始数据!"&"F149:F154"
A30: 抗坏血酸 | B30: g·kg⁻¹ FW | C30: 0 | D30: =AVERAGE('试验原始数据'!$F$155:$F$157) | E30: =STDEV.S('试验原始数据'!$F$155:$F$157) | F30: =AVERAGE('试验原始数据'!$F$158:$F$160) | G30: =STDEV.S('试验原始数据'!$F$158:$F$160) | H30: =F30-D30 | I30: =IF(D30=0,"",H30/ABS(D30)) | J30: =IF(AND(E30=0,G30=0),IF(H30=0,1,""),T.TEST('试验原始数据'!$F$155:$F$157,'试验原始数据'!$F$158:$F$160,2,3)) | K30: =IF(J30="","",MIN(1,J30*30)) | L30: =IF(H30>0,"GA₃高于CK",IF(H30<0,"GA₃低于CK","无差异")) | M30: ="试验原始数据!"&"F155:F160"
A31: 抗坏血酸 | B31: g·kg⁻¹ FW | C31: 7 | D31: =AVERAGE('试验原始数据'!$F$161:$F$163) | E31: =STDEV.S('试验原始数据'!$F$161:$F$163) | F31: =AVERAGE('试验原始数据'!$F$164:$F$166) | G31: =STDEV.S('试验原始数据'!$F$164:$F$166) | H31: =F31-D31 | I31: =IF(D31=0,"",H31/ABS(D31)) | J31: =IF(AND(E31=0,G31=0),IF(H31=0,1,""),T.TEST('试验原始数据'!$F$161:$F$163,'试验原始数据'!$F$164:$F$166,2,3)) | K31: =IF(J31="","",MIN(1,J31*30)) | L31: =IF(H31>0,"GA₃高于CK",IF(H31<0,"GA₃低于CK","无差异")) | M31: ="试验原始数据!"&"F161:F166"
A32: 抗坏血酸 | B32: g·kg⁻¹ FW | C32: 14 | D32: =AVERAGE('试验原始数据'!$F$167:$F$169) | E32: =STDEV.S('试验原始数据'!$F$167:$F$169) | F32: =AVERAGE('试验原始数据'!$F$170:$F$172) | G32: =STDEV.S('试验原始数据'!$F$170:$F$172) | H32: =F32-D32 | I32: =IF(D32=0,"",H32/ABS(D32)) | J32: =IF(AND(E32=0,G32=0),IF(H32=0,1,""),T.TEST('试验原始数据'!$F$167:$F$169,'试验原始数据'!$F$170:$F$172,2,3)) | K32: =IF(J32="","",MIN(1,J32*30)) | L32: =IF(H32>0,"GA₃高于CK",IF(H32<0,"GA₃低于CK","无差异")) | M32: ="试验原始数据!"&"F167:F172"
A33: 抗坏血酸 | B33: g·kg⁻¹ FW | C33: 21 | D33: =AVERAGE('试验原始数据'!$F$173:$F$175) | E33: =STDEV.S('试验原始数据'!$F$173:$F$175) | F33: =AVERAGE('试验原始数据'!$F$176:$F$178) | G33: =STDEV.S('试验原始数据'!$F$176:$F$178) | H33: =F33-D33 | I33: =IF(D33=0,"",H33/ABS(D33)) | J33: =IF(AND(E33=0,G33=0),IF(H33=0,1,""),T.TEST('试验原始数据'!$F$173:$F$175,'试验原始数据'!$F$176:$F$178,2,3)) | K33: =IF(J33="","",MIN(1,J33*30)) | L33: =IF(H33>0,"GA₃高于CK",IF(H33<0,"GA₃低于CK","无差异")) | M33: ="试验原始数据!"&"F173:F178"
A34: 抗坏血酸 | B34: g·kg⁻¹ FW | C34: 28 | D34: =AVERAGE('试验原始数据'!$F$179:$F$181) | E34: =STDEV.S('试验原始数据'!$F$179:$F$181) | F34: =AVERAGE('试验原始数据'!$F$182:$F$184) | G34: =STDEV.S('试验原始数据'!$F$182:$F$184) | H34: =F34-D34 | I34: =IF(D34=0,"",H34/ABS(D34)) | J34: =IF(AND(E34=0,G34=0),IF(H34=0,1,""),T.TEST('试验原始数据'!$F$179:$F$181,'试验原始数据'!$F$182:$F$184,2,3)) | K34: =IF(J34="","",MIN(1,J34*30)) | L34: =IF(H34>0,"GA₃高于CK",IF(H34<0,"GA₃低于CK","无差异")) | M34: ="试验原始数据!"&"F179:F184"

Sheet 采购批次
A1: 采购批次
A2: 来源：企业经营数据样例/01_采购批次台账.xlsx。保留原始逐笔记录；日期、数量、金额和比例按字段类型呈现。
A4: 批次号 | B4: 品种 | C4: 产地 | D4: 采收日期 | E4: 到仓日期 | F4: 到仓仓库 | G4: 到货量kg | H4: 采购单价元kg | I4: 采购金额元 | J4: 采购方式 | K4: 到仓硬度kgf | L4: 到仓糖度Brix | M4: 计划销售渠道 | N4: 批次状态
A5: NY-KW-2508-001 | B5: 金艳 | C5: 湖北建始基地 | D5: 45891 | E5: 45894 | F5: 深圳龙岗前置仓 | G5: 9000 | H5: 8.48 | I5: 76320 | J5: 基地直采 | K5: 7.48 | L5: 8.7 | M5: 企业团购 | N5: 已结批
A6: NY-KW-2508-002 | B6: 金艳 | C6: 湖北建始基地 | D6: 45936 | E6: 45938 | F6: 广州黄埔仓 | G6: 11600 | H6: 6.22 | I6: 72152 | J6: 基地直采 | K6: 8.45 | L6: 8.3 | M6: 连锁门店 | N6: 已结批
A7: NY-KW-2508-003 | B7: 海沃德 | C7: 广西桂林合作基地 | D7: 45920 | E7: 45921 | F7: 南宁江南分仓 | G7: 10000 | H7: 8.1 | I7: 81000 | J7: 产地经纪采购 | K7: 6.37 | L7: 7.6 | M7: 混合渠道 | N7: 已结批
A8: NY-KW-2508-004 | B8: 徐香 | C8: 陕西周至合作社 | D8: 45936 | E8: 45937 | F8: 广州黄埔仓 | G8: 14000 | H8: 6.21 | I8: 86940 | J8: 基地直采 | K8: 6.34 | L8: 9.4 | M8: 连锁门店 | N8: 已结批
A9: NY-KW-2508-005 | B9: 翠香 | C9: 广西桂林合作基地 | D9: 45928 | E9: 45930 | F9: 南宁江南分仓 | G9: 19000 | H9: 7.28 | I9: 138320 | J9: 基地直采 | K9: 8.13 | L9: 8.4 | M9: 社区电商 | N9: 已结批
A10: NY-KW-2508-006 | B10: 翠香 | C10: 四川蒲江基地 | D10: 45899 | E10: 45903 | F10: 深圳龙岗前置仓 | G10: 16400 | H10: 7 | I10: 114800 | J10: 产地经纪采购 | K10: 7.25 | L10: 7.3 | M10: 连锁门店 | N10: 已结批
A11: NY-KW-2508-007 | B11: 金艳 | C11: 湖北建始基地 | D11: 45921 | E11: 45924 | F11: 广州黄埔仓 | G11: 19400 | H11: 8.05 | I11: 156170 | J11: 基地直采 | K11: 6.85 | L11: 6.9 | M11: 社区电商 | N11: 已结批
A12: NY-KW-2508-008 | B12: 海沃德 | C12: 湖北建始基地 | D12: 45933 | E12: 45936 | F12: 深圳龙岗前置仓 | G12: 22300 | H12: 8.23 | I12: 183529 | J12: 基地直采 | K12: 6.33 | L12: 9.4 | M12: 混合渠道 | N12: 已结批
A13: NY-KW-2508-009 | B13: 翠香 | C13: 湖北建始基地 | D13: 45921 | E13: 45925 | F13: 深圳龙岗前置仓 | G13: 22700 | H13: 8.08 | I13: 183416 | J13: 产地经纪采购 | K13: 7.96 | L13: 9.6 | M13: 连锁门店 | N13: 已结批
A14: NY-KW-2508-010 | B14: 海沃德 | C14: 贵州修文基地 | D14: 45946 | E14: 45949 | F14: 深圳龙岗前置仓 | G14: 22700 | H14: 8.91 | I14: 202257 | J14: 基地直采 | K14: 6.59 | L14: 10 | M14: 连锁门店 | N14: 已结批
A15: NY-KW-2508-011 | B15: 海沃德 | C15: 广西桂林合作基地 | D15: 45920 | E15: 45924 | F15: 南宁江南分仓 | G15: 21300 | H15: 7.38 | I15: 157194 | J15: 基地直采 | K15: 8.55 | L15: 7.8 | M15: 连锁门店 | N15: 已结批
A16: NY-KW-2508-012 | B16: 海沃德 | C16: 贵州修文基地 | D16: 45914 | E16: 45918 | F16: 广州黄埔仓 | G16: 21300 | H16: 8.07 | I16: 171891 | J16: 合作社采购 | K16: 7.61 | L16: 8.9 | M16: 企业团购 | N16: 已结批
... A32: NY-KW-2508-028 | B32: 徐香 | C32: 四川蒲江基地 | D32: 45922 | E32: 45926 | F32: 深圳龙岗前置仓 | G32: 16600 | H32: 7.81 | I32: 129646 | J32: 产地经纪采购 | K32: 7.69 | L32: 7.6 | M32: 连锁门店 | N32: 已结批

Sheet 库存流水
A1: 库存流水
A2: 来源：企业经营数据样例/02_库存出入库流水.xlsx。保留原始逐笔记录；日期、数量、金额和比例按字段类型呈现。
A4: 日期 | B4: 批次号 | C4: 仓库 | D4: 期初库存kg | E4: 入库kg | F4: 出库kg | G4: 报损kg | H4: 期末库存kg | I4: 入库后天数 | J4: 库位类型 | K4: 出库去向 | L4: 是否末笔
A5: 45894 | B5: NY-KW-2508-001 | C5: 深圳龙岗前置仓 | D5: 0 | E5: 9000 | F5: 2109 | G5: 103.5 | H5: 6787.5 | I5: 0 | J5: 冷藏库 | K5: 电商发货 | L5: 0
A6: 45895 | B6: NY-KW-2508-001 | C6: 深圳龙岗前置仓 | D6: 6787.5 | E6: 0 | F6: 1654 | G6: 89.2 | H6: 5044.3 | I6: 1 | J6: 前置仓 | K6: 未分配 | L6: 0
A7: 45896 | B7: NY-KW-2508-001 | C7: 深圳龙岗前置仓 | D7: 5044.3 | E7: 0 | F7: 1368.9 | G7: 35.4 | H7: 3640 | I7: 2 | J7: 前置仓 | K7: 未分配 | L7: 0
A8: 45897 | B8: NY-KW-2508-001 | C8: 深圳龙岗前置仓 | D8: 3640 | E8: 0 | F8: 1005.1 | G8: 44.9 | H8: 2590 | I8: 3 | J8: 暂存区 | K8: 批发出库 | L8: 0
A9: 45898 | B9: NY-KW-2508-001 | C9: 广州黄埔仓 | D9: 2590 | E9: 0 | F9: 1001.6 | G9: 25.8 | H9: 1562.6 | I9: 4 | J9: 冷藏库 | K9: 批发出库 | L9: 0
A10: 45899 | B10: NY-KW-2508-001 | C10: 深圳龙岗前置仓 | D10: 1562.6 | E10: 0 | F10: 1555.9 | G10: 6.7 | H10: 0 | I10: 5 | J10: 冷藏库 | K10: 批发出库 | L10: 0
A11: 45900 | B11: NY-KW-2508-001 | C11: 南宁江南分仓 | D11: 0 | E11: 0 | F11: 0 | G11: 0 | H11: 0 | I11: 6 | J11: 冷藏库 | K11: 门店补货 | L11: 1
A12: 45938 | B12: NY-KW-2508-002 | C12: 广州黄埔仓 | D12: 0 | E12: 11600 | F12: 1464.6 | G12: 30 | H12: 10105.4 | I12: 0 | J12: 暂存区 | K12: 批发出库 | L12: 0
A13: 45939 | B13: NY-KW-2508-002 | C13: 南宁江南分仓 | D13: 10105.4 | E13: 0 | F13: 2861.2 | G13: 93.6 | H13: 7150.6 | I13: 1 | J13: 前置仓 | K13: 门店补货 | L13: 0
A14: 45940 | B14: NY-KW-2508-002 | C14: 南宁江南分仓 | D14: 7150.6 | E14: 0 | F14: 1828.5 | G14: 20.8 | H14: 5301.3 | I14: 2 | J14: 前置仓 | K14: 门店补货 | L14: 0
A15: 45941 | B15: NY-KW-2508-002 | C15: 南宁江南分仓 | D15: 5301.3 | E15: 0 | F15: 1574.6 | G15: 35.1 | H15: 3691.6 | I15: 3 | J15: 暂存区 | K15: 未分配 | L15: 0
A16: 45942 | B16: NY-KW-2508-002 | C16: 深圳龙岗前置仓 | D16: 3691.6 | E16: 0 | F16: 2942.3 | G16: 4.5 | H16: 744.8 | I16: 4 | J16: 前置仓 | K16: 未分配 | L16: 1
... A207: 45933 | B207: NY-KW-2508-028 | C207: 南宁江南分仓 | D207: 0 | E207: 0 | F207: 0 | G207: 0 | H207: 0 | I207: 7 | J207: 前置仓 | K207: 未分配 | L207: 1

Sheet 报损折价
A1: 报损折价
A2: 来源：企业经营数据样例/03_报损与折价处理记录.xlsx。保留原始逐笔记录；日期、数量、金额和比例按字段类型呈现。
A4: 单据号 | B4: 记录日期 | C4: 批次号 | D4: 发生环节 | E4: 问题类型 | F4: 问题数量kg | G4: 报废kg | H4: 折价处理kg | I4: 估计损失元 | J4: 是否和成熟相关 | K4: 处理备注
A5: BS-2508-0001 | B5: 45910 | C5: NY-KW-2508-006 | D5: 仓库分拣 | E5: 过熟偏软 | F5: 356.1 | G5: 202.7 | H5: 153.4 | I5: 1754.51 | J5: 是 | K5: 正常记录
A6: BS-2508-0002 | B6: 45941 | C6: NY-KW-2508-002 | D6: 门店收货 | E6: 软烂 | F6: 73.1 | G6: 49.3 | H6: 23.8 | I6: 371.5 | J6: 是 | K6: 门店已反馈
A7: BS-2508-0003 | B7: 45927 | C7: NY-KW-2508-009 | D7: 仓库分拣 | E7: 表皮皱缩 | F7: 401.2 | G7: 199.7 | H7: 201.5 | I7: 2286.25 | J7: 否 | K7: 门店已反馈
A8: BS-2508-0004 | B8: 45908 | C8: NY-KW-2508-006 | D8: 运输到货 | E8: 过熟偏软 | F8: 397.8 | G8: 134.9 | H8: 262.9 | I8: 1543.3 | J8: 是 | K8: 已和采购沟通
A9: BS-2508-0005 | B9: 45931 | C9: NY-KW-2508-007 | D9: 仓库分拣 | E9: 过熟偏软 | F9: 47.2 | G9: 29.7 | H9: 17.5 | I9: 295.37 | J9: 是 | K9: 门店已反馈
A10: BS-2508-0006 | B10: 45942 | C10: NY-KW-2508-014 | D10: 门店收货 | E10: 规格不符 | F10: 373 | G10: 213.8 | H10: 159.2 | I10: 1560.82 | J10: 否 | K10: 门店已反馈
A11: BS-2508-0007 | B11: 45927 | C11: NY-KW-2508-020 | D11: 门店收货 | E11: 过熟偏软 | F11: 104.3 | G11: 28.5 | H11: 75.8 | I11: 362.48 | J11: 是 | K11: 需复盘
A12: BS-2508-0008 | B12: 45933 | C12: NY-KW-2508-005 | D12: 客户退货 | E12: 软烂 | F12: 66.7 | G12: 36.3 | H12: 30.4 | I12: 345.51 | J12: 是 | K12: 已和采购沟通
A13: BS-2508-0009 | B13: 45952 | C13: NY-KW-2508-015 | D13: 门店收货 | E13: 碰压伤 | F13: 415.5 | G13: 111.4 | H13: 304.1 | I13: 1351.59 | J13: 否 | K13: 需复盘
A14: BS-2508-0010 | B14: 45943 | C14: NY-KW-2508-002 | D14: 客户退货 | E14: 过熟偏软 | F14: 202.6 | G14: 86.5 | H14: 116.1 | I14: 779.2 | J14: 是 | K14: 需复盘
A15: BS-2508-0011 | B15: 45927 | C15: NY-KW-2508-024 | D15: 客户退货 | E15: 规格不符 | F15: 109.4 | G15: 38.5 | H15: 70.9 | I15: 393.84 | J15: 否 | K15: 已和采购沟通
A16: BS-2508-0012 | B16: 45912 | C16: NY-KW-2508-006 | D16: 仓库分拣 | E16: 软烂 | F16: 190.5 | G16: 90.3 | H16: 100.2 | I16: 853.11 | J16: 是 | K16: 已和采购沟通
... A79: BS-2508-0075 | B79: 45944 | C79: NY-KW-2508-004 | D79: 运输到货 | E79: 软烂 | F79: 394.6 | G79: 239.3 | H79: 155.3 | I79: 1830.76 | J79: 是 | K79: 需复盘

Sheet 销售流水
A1: 销售流水
A2: 来源：企业经营数据样例/04_销售流水与价格记录.xlsx。保留原始逐笔记录；日期、数量、金额和比例按字段类型呈现。
A4: 销售单号 | B4: 销售日期 | C4: 批次号 | D4: 渠道 | E4: 城市 | F4: 销售kg | G4: 原价销售kg | H4: 折价销售kg | I4: 平均售价元kg | J4: 销售收入元 | K4: 退货kg | L4: 客诉件数 | M4: 客诉原因
A5: XS-2508-00001 | B5: 45895 | C5: NY-KW-2508-001 | D5: 批发客户 | E5: 佛山 | F5: 696.8 | G5: 553.8 | H5: 143 | I5: 25.12 | J5: 17503.62 | K5: 11.6 | L5: 1 | M5: 风味一般
A6: XS-2508-00002 | B6: 45896 | C6: NY-KW-2508-001 | D6: 社区电商 | E6: 深圳 | F6: 843.8 | G6: 807.4 | H6: 36.4 | I6: 25.51 | J6: 21525.34 | K6: 4.5 | L6: 0 | M6: 无
A7: XS-2508-00003 | B7: 45897 | C7: NY-KW-2508-001 | D7: 连锁门店 | E7: 惠州 | F7: 1330.2 | G7: 921.1 | H7: 409.1 | I7: 26.04 | J7: 34638.41 | K7: 9 | L7: 0 | M7: 无
A8: XS-2508-00004 | B8: 45898 | C8: NY-KW-2508-001 | D8: 连锁门店 | E8: 惠州 | F8: 1040.6 | G8: 848.5 | H8: 192.1 | I8: 24.92 | J8: 25931.75 | K8: 12.4 | L8: 1 | M8: 偏硬
A9: XS-2508-00005 | B9: 45899 | C9: NY-KW-2508-001 | D9: 连锁门店 | E9: 深圳 | F9: 273 | G9: 225.1 | H9: 47.9 | I9: 28.8 | J9: 7862.4 | K9: 0.6 | L9: 2 | M9: 外观
A10: XS-2508-00006 | B10: 45900 | C10: NY-KW-2508-001 | D10: 连锁门店 | E10: 广州 | F10: 184.2 | G10: 104.3 | H10: 79.9 | I10: 23.96 | J10: 4413.43 | K10: 3.2 | L10: 0 | M10: 无
A11: XS-2508-00007 | B11: 45901 | C11: NY-KW-2508-001 | D11: 连锁门店 | E11: 广州 | F11: 611.2 | G11: 383.8 | H11: 227.4 | I11: 30.65 | J11: 18733.28 | K11: 1.3 | L11: 0 | M11: 无
A12: XS-2508-00008 | B12: 45902 | C12: NY-KW-2508-001 | D12: 连锁门店 | E12: 广州 | F12: 451 | G12: 337.7 | H12: 113.3 | I12: 24.18 | J12: 10905.18 | K12: 3.4 | L12: 0 | M12: 无
A13: XS-2508-00009 | B13: 45903 | C13: NY-KW-2508-001 | D13: 社区电商 | E13: 广州 | F13: 1281.1 | G13: 903.6 | H13: 377.5 | I13: 27.82 | J13: 35640.2 | K13: 17 | L13: 0 | M13: 无
A14: XS-2508-00010 | B14: 45939 | C14: NY-KW-2508-002 | D14: 连锁门店 | E14: 东莞 | F14: 821 | G14: 745.1 | H14: 75.9 | I14: 24.37 | J14: 20007.77 | K14: 14.4 | L14: 1 | M14: 风味一般
A15: XS-2508-00011 | B15: 45940 | C15: NY-KW-2508-002 | D15: 连锁门店 | E15: 佛山 | F15: 828.8 | G15: 749 | H15: 79.8 | I15: 18.22 | J15: 15100.74 | K15: 11.1 | L15: 0 | M15: 无
A16: XS-2508-00012 | B16: 45941 | C16: NY-KW-2508-002 | D16: 连锁门店 | E16: 深圳 | F16: 1518.9 | G16: 1382.6 | H16: 136.3 | I16: 25.35 | J16: 38504.12 | K16: 25.8 | L16: 3 | M16: 偏软
... A203: XS-2508-00199 | B203: 45931 | C203: NY-KW-2508-028 | D203: 连锁门店 | E203: 广州 | F203: 593.6 | G203: 476.5 | H203: 117.1 | I203: 27.74 | J203: 16466.46 | K203: 2.6 | L203: 0 | M203: 无

Sheet 冷链温控
A1: 冷链温控
A2: 来源：企业经营数据样例/05_冷链温控记录.xlsx。保留原始逐笔记录；日期、数量、金额和比例按字段类型呈现。
A4: 批次号 | B4: 环节 | C4: 开始时间 | D4: 结束时间 | E4: 平均温度℃ | F4: 最高温度℃ | G4: 最低温度℃ | H4: 超温小时 | I4: 平均湿度 | J4: 是否断链 | K4: 记录备注
A5: NY-KW-2508-001 | B5: 预冷 | C5: 45894 | D5: 45894.583 | E5: 2 | F5: 6.4 | G5: 1.2 | H5: 0.5 | I5: 0.846 | J5: 否 | K5: 到店后常温暴露偏长
A6: NY-KW-2508-001 | B6: 主仓冷藏 | C6: 45894.333 | D6: 45897.417 | E6: 4.3 | F6: 7 | G6: 3.1 | H6: 0.3 | I6: 0.89 | J6: 否 | K6: 温度波动
A7: NY-KW-2508-001 | B7: 干线运输 | C7: 45897.333 | D7: 45897.917 | E7: 6.4 | F7: 8.3 | G7: 4.4 | H7: 1.2 | I7: 0.825 | J7: 否 | K7: 需关注
A8: NY-KW-2508-001 | B8: 分仓暂存 | C8: 45897.833 | D8: 45898.958 | E8: 2.7 | F8: 4.7 | G8: 1.6 | H8: 0 | I8: 0.853 | J8: 否 | K8: 到店后常温暴露偏长
A9: NY-KW-2508-001 | B9: 门店货架 | C9: 45898.833 | D9: 45900.25 | E9: 16.1 | F9: 19.2 | G9: 13.7 | H9: 4.2 | I9: 0.862 | J9: 否 | K9: 需关注
A10: NY-KW-2508-002 | B10: 预冷 | C10: 45938 | D10: 45938.583 | E10: 1.8 | F10: 5.9 | G10: 0 | H10: 0 | I10: 0.878 | J10: 否 | K10: 到店后常温暴露偏长
A11: NY-KW-2508-002 | B11: 主仓冷藏 | C11: 45938.333 | D11: 45941.333 | E11: 4 | F11: 6.5 | G11: 2.3 | H11: 0.3 | I11: 0.83 | J11: 否 | K11: 温度波动
A12: NY-KW-2508-002 | B12: 干线运输 | C12: 45941.333 | D12: 45941.875 | E12: 3.7 | F12: 8.4 | G12: 3 | H12: 3.4 | I12: 0.833 | J12: 否 | K12: 正常
A13: NY-KW-2508-002 | B13: 分仓暂存 | C13: 45941.833 | D13: 45943.083 | E13: 2.2 | F13: 5.7 | G13: 0 | H13: 0 | I13: 0.868 | J13: 否 | K13: 需关注
A14: NY-KW-2508-002 | B14: 门店货架 | C14: 45942.833 | D14: 45944.375 | E14: 18.1 | F14: 23.5 | G14: 16.1 | H14: 2.2 | I14: 0.916 | J14: 否 | K14: 到店后常温暴露偏长
A15: NY-KW-2508-003 | B15: 预冷 | C15: 45921 | D15: 45921.583 | E15: 1.7 | F15: 3.8 | G15: 0.7 | H15: 0 | I15: 0.921 | J15: 否 | K15: 正常
A16: NY-KW-2508-003 | B16: 主仓冷藏 | C16: 45921.333 | D16: 45924.375 | E16: 4.4 | F16: 6.8 | G16: 3.3 | H16: 0.4 | I16: 0.91 | J16: 否 | K16: 温度波动
... A144: NY-KW-2508-028 | B144: 门店货架 | C144: 45930.833 | D144: 45932.458 | E144: 15 | F144: 18 | G144: 12.9 | H144: 1 | I144: 0.869 | J144: 否 | K144: 到店后常温暴露偏长

Sheet 质检抽检
A1: 质检抽检
A2: 来源：企业经营数据样例/06_质检抽检记录.xlsx。保留原始逐笔记录；日期、数量、金额和比例按字段类型呈现。
A4: 检测日期 | B4: 批次号 | C4: 入库后天数 | D4: 抽检果数 | E4: 平均硬度kgf | F4: 糖度Brix | G4: 外观等级 | H4: 销售建议 | I4: 主要问题 | J4: 检测小组
A5: 45894 | B5: NY-KW-2508-001 | C5: 0 | D5: 15 | E5: 7.48 | F5: 8.7 | G5: A | H5: 可售 | I5: 偏硬 | J5: 南宁质检组
A6: 45896 | B6: NY-KW-2508-001 | C6: 2 | D6: 15 | E6: 6.27 | F6: 9.3 | G6: A | H6: 可售 | I6: 无 | J6: 广州质检组
A7: 45898 | B7: NY-KW-2508-001 | C7: 4 | D7: 20 | E7: 5.21 | F7: 10.6 | G7: A | H7: 可售 | I7: 适熟 | J7: 南宁质检组
A8: 45900 | B8: NY-KW-2508-001 | C8: 6 | D8: 12 | E8: 5.11 | F8: 12.2 | G8: B | H8: 可售 | I8: 偏硬 | J8: 南宁质检组
A9: 45902 | B9: NY-KW-2508-001 | C9: 8 | D9: 12 | E9: 4.36 | F9: 12.4 | G9: B | H9: 临界 | I9: 适熟 | J9: 南宁质检组
A10: 45938 | B10: NY-KW-2508-002 | C10: 0 | D10: 12 | E10: 8.45 | F10: 8.3 | G10: A | H10: 可售 | I10: 偏硬 | J10: 广州质检组
A11: 45940 | B11: NY-KW-2508-002 | C11: 2 | D11: 20 | E11: 7.39 | F11: 9.4 | G11: B | H11: 可售 | I11: 适熟 | J11: 广州质检组
A12: 45942 | B12: NY-KW-2508-002 | C12: 4 | D12: 15 | E12: 6.79 | F12: 9.7 | G12: A | H12: 可售 | I12: 适熟 | J12: 深圳质检组
A13: 45944 | B13: NY-KW-2508-002 | C13: 6 | D13: 20 | E13: 3.67 | F13: 12.2 | G13: C | H13: 临界 | I13: 偏软 | J13: 深圳质检组
A14: 45946 | B14: NY-KW-2508-002 | C14: 8 | D14: 12 | E14: 3.88 | F14: 12.4 | G14: C | H14: 临界 | I14: 适熟 | J14: 深圳质检组
A15: 45921 | B15: NY-KW-2508-003 | C15: 0 | D15: 15 | E15: 6.37 | F15: 7.6 | G15: A | H15: 可售 | I15: 偏硬 | J15: 南宁质检组
A16: 45923 | B16: NY-KW-2508-003 | C16: 2 | D16: 12 | E16: 4.96 | F16: 8.2 | G16: A | H16: 可售 | I16: 偏硬 | J16: 广州质检组
... A144: 45934 | B144: NY-KW-2508-028 | C144: 8 | D144: 20 | E144: 3.39 | F144: 10.1 | G144: C | H144: 临界 | I144: 适熟 | J144: 南宁质检组

Sheet 处理成本
A1: 处理成本
A2: 来源：企业经营数据样例/07_采后处理成本记录.xlsx。保留原始逐笔记录；日期、数量、金额和比例按字段类型呈现。
A4: 月份 | B4: 费用项目 | C4: 计量单位 | D4: 参考单价 | E4: 口径说明 | F4: 负责部门
A5: 2025-08 | B5: 处理药剂 | C5: 元/kg果 | D5: 0.03 | E5: 按试点采购价和使用量折算 | F5: 研发中心
A6: 2025-08 | B6: 现场人工 | C6: 元/kg果 | D6: 0.049 | E6: 增加分拣和处理工时 | F6: 仓储部
A7: 2025-08 | B7: 设备折旧 | C7: 元/kg果 | D7: 0.025 | E7: 处理池/喷淋设备按处理量分摊 | F7: 运营部
A8: 2025-08 | B8: 残留检测 | C8: 元/批 | D8: 848.521 | E8: 送检费用，实际以检测机构报价为准 | F8: 质量部
A9: 2025-08 | B9: 品质复检 | C9: 元/批 | D9: 237.863 | E9: 硬度、糖度、外观抽检 | F9: 质量部
A10: 2025-08 | B10: 记录与追溯 | C10: 元/批 | D10: 83.646 | E10: 扫码、批次记录、表单维护 | F10: 仓储部
A11: 2025-08 | B11: 废液处理 | C11: 元/批 | D11: 294.607 | E11: 如采用浸泡方式需计入 | F11: 运营部
A12: 2025-08 | B12: 员工培训 | C12: 元/月 | D12: 4960.821 | E12: 试点期培训和SOP执行 | F12: 运营部
A13: 2025-09 | B13: 处理药剂 | C13: 元/kg果 | D13: 0.031 | E13: 按试点采购价和使用量折算 | F13: 研发中心
A14: 2025-09 | B14: 现场人工 | C14: 元/kg果 | D14: 0.048 | E14: 增加分拣和处理工时 | F14: 仓储部
A15: 2025-09 | B15: 设备折旧 | C15: 元/kg果 | D15: 0.022 | E15: 处理池/喷淋设备按处理量分摊 | F15: 运营部
A16: 2025-09 | B16: 残留检测 | C16: 元/批 | D16: 884.277 | E16: 送检费用，实际以检测机构报价为准 | F16: 质量部
... A28: 2025-10 | B28: 员工培训 | C28: 元/月 | D28: 5284.588 | E28: 试点期培训和SOP执行 | F28: 运营部

Sheet 渠道动销
A1: 渠道动销
A2: 来源：企业经营数据样例/08_渠道到货与动销表现.xlsx。保留原始逐笔记录；日期、数量、金额和比例按字段类型呈现。
A4: 到货单号 | B4: 到货日期 | C4: 批次号 | D4: 渠道 | E4: 城市 | F4: 到货kg | G4: 可正常销售kg | H4: 到货偏软比例 | I4: 折价销售比例 | J4: 售完天数 | K4: 渠道反馈
A5: DH-2508-0001 | B5: 45924 | C5: NY-KW-2508-020 | D5: 连锁门店 | E5: 广州 | F5: 415.4 | G5: 363.9 | H5: 0.124 | I5: 0.102 | J5: 2.5 | K5: 正常
A6: DH-2508-0002 | B6: 45956 | C6: NY-KW-2508-010 | D6: 连锁门店 | E6: 东莞 | F6: 129 | G6: 124.6 | H6: 0.034 | I6: 0.031 | J6: 4.6 | K6: 正常
A7: DH-2508-0003 | B7: 45924 | C7: NY-KW-2508-019 | D7: 社区电商 | E7: 惠州 | F7: 169.9 | G7: 160.7 | H7: 0.054 | I7: 0.057 | J7: 3.4 | K7: 动销慢
A8: DH-2508-0004 | B8: 45923 | C8: NY-KW-2508-012 | D8: 批发客户 | E8: 惠州 | F8: 819.4 | G8: 763.7 | H8: 0.068 | I8: 0.075 | J8: 1.8 | K8: 补货及时
A9: DH-2508-0005 | B9: 45955 | C9: NY-KW-2508-010 | D9: 批发客户 | E9: 东莞 | F9: 661.4 | G9: 545 | H9: 0.176 | I9: 0.126 | J9: 4.6 | K9: 补货及时
A10: DH-2508-0006 | B10: 45933 | C10: NY-KW-2508-017 | D10: 连锁门店 | E10: 深圳 | F10: 683 | G10: 633.1 | H10: 0.073 | I10: 0.041 | J10: 3.5 | K10: 偏软反馈
A11: DH-2508-0007 | B11: 45927 | C11: NY-KW-2508-028 | D11: 连锁门店 | E11: 南宁 | F11: 622.4 | G11: 548.3 | H11: 0.119 | I11: 0.061 | J11: 1.8 | K11: 正常
A12: DH-2508-0008 | B12: 45915 | C12: NY-KW-2508-023 | D12: 企业团购 | E12: 东莞 | F12: 1092.9 | G12: 997.8 | H12: 0.087 | I12: 0.055 | J12: 2.4 | K12: 正常
A13: DH-2508-0009 | B13: 45897 | C13: NY-KW-2508-001 | D13: 社区电商 | E13: 珠海 | F13: 1046.1 | G13: 953 | H13: 0.089 | I13: 0.06 | J13: 4.3 | K13: 正常
A14: DH-2508-0010 | B14: 45910 | C14: NY-KW-2508-026 | D14: 社区电商 | E14: 东莞 | F14: 422.1 | G14: 386.6 | H14: 0.084 | I14: 0.09 | J14: 4.1 | K14: 正常
A15: DH-2508-0011 | B15: 45928 | C15: NY-KW-2508-009 | D15: 社区电商 | E15: 深圳 | F15: 1102.2 | G15: 921.4 | H15: 0.164 | I15: 0.133 | J15: 3.7 | K15: 补货及时
A16: DH-2508-0012 | B16: 45955 | C16: NY-KW-2508-010 | D16: 连锁门店 | E16: 佛山 | F16: 573.4 | G16: 552.2 | H16: 0.037 | I16: 0.047 | J16: 3.1 | K16: 补货及时
... A94: DH-2508-0090 | B94: 45925 | C94: NY-KW-2508-019 | D94: 社区电商 | E94: 南宁 | F94: 154.5 | G94: 142.1 | H94: 0.08 | I94: 0.101 | J94: 2.2 | K94: 偏软反馈

Sheet 批次对账
A1: 批次对账
A2: 以采购批次号为主键连接库存、报损、销售、冷链、质检和渠道数据；余额差异用于识别记录口径或覆盖范围问题。
A4: 批次号 | B4: 采购到货kg | C4: 库存入库kg | D4: 库存出库kg | E4: 库存报损kg | F4: 末笔期末库存kg | G4: 库存平衡差异kg | H4: 销售kg | I4: 销售/出库覆盖率 | J4: 成熟相关问题kg | K4: 冷链超温小时 | L4: 最低抽检硬度kgf | M4: 渠道到货kg
A5: NY-KW-2508-001 | B5: =SUMIF('采购批次'!$A$5:$A$32,A5,'采购批次'!$G$5:$G$32) | C5: =SUMIF('库存流水'!$B$5:$B$207,A5,'库存流水'!$E$5:$E$207) | D5: =SUMIF('库存流水'!$B$5:$B$207,A5,'库存流水'!$F$5:$F$207) | E5: =SUMIF('库存流水'!$B$5:$B$207,A5,'库存流水'!$G$5:$G$207) | F5: =SUMIFS('库存流水'!$H$5:$H$207,'库存流水'!$B$5:$B$207,A5,'库存流水'!$L$5:$L$207,1) | G5: =B5-D5-E5-F5 | H5: =SUMIF('销售流水'!$C$5:$C$203,A5,'销售流水'!$F$5:$F$203) | I5: =IF(D5=0,0,H5/D5) | J5: =SUMIFS('报损折价'!$F$5:$F$79,'报损折价'!$C$5:$C$79,A5,'报损折价'!$J$5:$J$79,"是") | K5: =SUMIF('冷链温控'!$A$5:$A$144,A5,'冷链温控'!$H$5:$H$144) | L5: =MINIFS('质检抽检'!$E$5:$E$144,'质检抽检'!$B$5:$B$144,A5) | M5: =SUMIF('渠道动销'!$C$5:$C$94,A5,'渠道动销'!$F$5:$F$94)
A6: NY-KW-2508-002 | B6: =SUMIF('采购批次'!$A$5:$A$32,A6,'采购批次'!$G$5:$G$32) | C6: =SUMIF('库存流水'!$B$5:$B$207,A6,'库存流水'!$E$5:$E$207) | D6: =SUMIF('库存流水'!$B$5:$B$207,A6,'库存流水'!$F$5:$F$207) | E6: =SUMIF('库存流水'!$B$5:$B$207,A6,'库存流水'!$G$5:$G$207) | F6: =SUMIFS('库存流水'!$H$5:$H$207,'库存流水'!$B$5:$B$207,A6,'库存流水'!$L$5:$L$207,1) | G6: =B6-D6-E6-F6 | H6: =SUMIF('销售流水'!$C$5:$C$203,A6,'销售流水'!$F$5:$F$203) | I6: =IF(D6=0,0,H6/D6) | J6: =SUMIFS('报损折价'!$F$5:$F$79,'报损折价'!$C$5:$C$79,A6,'报损折价'!$J$5:$J$79,"是") | K6: =SUMIF('冷链温控'!$A$5:$A$144,A6,'冷链温控'!$H$5:$H$144) | L6: =MINIFS('质检抽检'!$E$5:$E$144,'质检抽检'!$B$5:$B$144,A6) | M6: =SUMIF('渠道动销'!$C$5:$C$94,A6,'渠道动销'!$F$5:$F$94)
A7: NY-KW-2508-003 | B7: =SUMIF('采购批次'!$A$5:$A$32,A7,'采购批次'!$G$5:$G$32) | C7: =SUMIF('库存流水'!$B$5:$B$207,A7,'库存流水'!$E$5:$E$207) | D7: =SUMIF('库存流水'!$B$5:$B$207,A7,'库存流水'!$F$5:$F$207) | E7: =SUMIF('库存流水'!$B$5:$B$207,A7,'库存流水'!$G$5:$G$207) | F7: =SUMIFS('库存流水'!$H$5:$H$207,'库存流水'!$B$5:$B$207,A7,'库存流水'!$L$5:$L$207,1) | G7: =B7-D7-E7-F7 | H7: =SUMIF('销售流水'!$C$5:$C$203,A7,'销售流水'!$F$5:$F$203) | I7: =IF(D7=0,0,H7/D7) | J7: =SUMIFS('报损折价'!$F$5:$F$79,'报损折价'!$C$5:$C$79,A7,'报损折价'!$J$5:$J$79,"是") | K7: =SUMIF('冷链温控'!$A$5:$A$144,A7,'冷链温控'!$H$5:$H$144) | L7: =MINIFS('质检抽检'!$E$5:$E$144,'质检抽检'!$B$5:$B$144,A7) | M7: =SUMIF('渠道动销'!$C$5:$C$94,A7,'渠道动销'!$F$5:$F$94)
A8: NY-KW-2508-004 | B8: =SUMIF('采购批次'!$A$5:$A$32,A8,'采购批次'!$G$5:$G$32) | C8: =SUMIF('库存流水'!$B$5:$B$207,A8,'库存流水'!$E$5:$E$207) | D8: =SUMIF('库存流水'!$B$5:$B$207,A8,'库存流水'!$F$5:$F$207) | E8: =SUMIF('库存流水'!$B$5:$B$207,A8,'库存流水'!$G$5:$G$207) | F8: =SUMIFS('库存流水'!$H$5:$H$207,'库存流水'!$B$5:$B$207,A8,'库存流水'!$L$5:$L$207,1) | G8: =B8-D8-E8-F8 | H8: =SUMIF('销售流水'!$C$5:$C$203,A8,'销售流水'!$F$5:$F$203) | I8: =IF(D8=0,0,H8/D8) | J8: =SUMIFS('报损折价'!$F$5:$F$79,'报损折价'!$C$5:$C$79,A8,'报损折价'!$J$5:$J$79,"是") | K8: =SUMIF('冷链温控'!$A$5:$A$144,A8,'冷链温控'!$H$5:$H$144) | L8: =MINIFS('质检抽检'!$E$5:$E$144,'质检抽检'!$B$5:$B$144,A8) | M8: =SUMIF('渠道动销'!$C$5:$C$94,A8,'渠道动销'!$F$5:$F$94)
A9: NY-KW-2508-005 | B9: =SUMIF('采购批次'!$A$5:$A$32,A9,'采购批次'!$G$5:$G$32) | C9: =SUMIF('库存流水'!$B$5:$B$207,A9,'库存流水'!$E$5:$E$207) | D9: =SUMIF('库存流水'!$B$5:$B$207,A9,'库存流水'!$F$5:$F$207) | E9: =SUMIF('库存流水'!$B$5:$B$207,A9,'库存流水'!$G$5:$G$207) | F9: =SUMIFS('库存流水'!$H$5:$H$207,'库存流水'!$B$5:$B$207,A9,'库存流水'!$L$5:$L$207,1) | G9: =B9-D9-E9-F9 | H9: =SUMIF('销售流水'!$C$5:$C$203,A9,'销售流水'!$F$5:$F$203) | I9: =IF(D9=0,0,H9/D9) | J9: =SUMIFS('报损折价'!$F$5:$F$79,'报损折价'!$C$5:$C$79,A9,'报损折价'!$J$5:$J$79,"是") | K9: =SUMIF('冷链温控'!$A$5:$A$144,A9,'冷链温控'!$H$5:$H$144) | L9: =MINIFS('质检抽检'!$E$5:$E$144,'质检抽检'!$B$5:$B$144,A9) | M9: =SUMIF('渠道动销'!$C$5:$C$94,A9,'渠道动销'!$F$5:$F$94)
A10: NY-KW-2508-006 | B10: =SUMIF('采购批次'!$A$5:$A$32,A10,'采购批次'!$G$5:$G$32) | C10: =SUMIF('库存流水'!$B$5:$B$207,A10,'库存流水'!$E$5:$E$207) | D10: =SUMIF('库存流水'!$B$5:$B$207,A10,'库存流水'!$F$5:$F$207) | E10: =SUMIF('库存流水'!$B$5:$B$207,A10,'库存流水'!$G$5:$G$207) | F10: =SUMIFS('库存流水'!$H$5:$H$207,'库存流水'!$B$5:$B$207,A10,'库存流水'!$L$5:$L$207,1) | G10: =B10-D10-E10-F10 | H10: =SUMIF('销售流水'!$C$5:$C$203,A10,'销售流水'!$F$5:$F$203) | I10: =IF(D10=0,0,H10/D10) | J10: =SUMIFS('报损折价'!$F$5:$F$79,'报损折价'!$C$5:$C$79,A10,'报损折价'!$J$5:$J$79,"是") | K10: =SUMIF('冷链温控'!$A$5:$A$144,A10,'冷链温控'!$H$5:$H$144) | L10: =MINIFS('质检抽检'!$E$5:$E$144,'质检抽检'!$B$5:$B$144,A10) | M10: =SUMIF('渠道动销'!$C$5:$C$94,A10,'渠道动销'!$F$5:$F$94)
A11: NY-KW-2508-007 | B11: =SUMIF('采购批次'!$A$5:$A$32,A11,'采购批次'!$G$5:$G$32) | C11: =SUMIF('库存流水'!$B$5:$B$207,A11,'库存流水'!$E$5:$E$207) | D11: =SUMIF('库存流水'!$B$5:$B$207,A11,'库存流水'!$F$5:$F$207) | E11: =SUMIF('库存流水'!$B$5:$B$207,A11,'库存流水'!$G$5:$G$207) | F11: =SUMIFS('库存流水'!$H$5:$H$207,'库存流水'!$B$5:$B$207,A11,'库存流水'!$L$5:$L$207,1) | G11: =B11-D11-E11-F11 | H11: =SUMIF('销售流水'!$C$5:$C$203,A11,'销售流水'!$F$5:$F$203) | I11: =IF(D11=0,0,H11/D11) | J11: =SUMIFS('报损折价'!$F$5:$F$79,'报损折价'!$C$5:$C$79,A11,'报损折价'!$J$5:$J$79,"是") | K11: =SUMIF('冷链温控'!$A$5:$A$144,A11,'冷链温控'!$H$5:$H$144) | L11: =MINIFS('质检抽检'!$E$5:$E$144,'质检抽检'!$B$5:$B$144,A11) | M11: =SUMIF('渠道动销'!$C$5:$C$94,A11,'渠道动销'!$F$5:$F$94)
A12: NY-KW-2508-008 | B12: =SUMIF('采购批次'!$A$5:$A$32,A12,'采购批次'!$G$5:$G$32) | C12: =SUMIF('库存流水'!$B$5:$B$207,A12,'库存流水'!$E$5:$E$207) | D12: =SUMIF('库存流水'!$B$5:$B$207,A12,'库存流水'!$F$5:$F$207) | E12: =SUMIF('库存流水'!$B$5:$B$207,A12,'库存流水'!$G$5:$G$207) | F12: =SUMIFS('库存流水'!$H$5:$H$207,'库存流水'!$B$5:$B$207,A12,'库存流水'!$L$5:$L$207,1) | G12: =B12-D12-E12-F12 | H12: =SUMIF('销售流水'!$C$5:$C$203,A12,'销售流水'!$F$5:$F$203) | I12: =IF(D12=0,0,H12/D12) | J12: =SUMIFS('报损折价'!$F$5:$F$79,'报损折价'!$C$5:$C$79,A12,'报损折价'!$J$5:$J$79,"是") | K12: =SUMIF('冷链温控'!$A$5:$A$144,A12,'冷链温控'!$H$5:$H$144) | L12: =MINIFS('质检抽检'!$E$5:$E$144,'质检抽检'!$B$5:$B$144,A12) | M12: =SUMIF('渠道动销'!$C$5:$C$94,A12,'渠道动销'!$F$5:$F$94)
A13: NY-KW-2508-009 | B13: =SUMIF('采购批次'!$A$5:$A$32,A13,'采购批次'!$G$5:$G$32) | C13: =SUMIF('库存流水'!$B$5:$B$207,A13,'库存流水'!$E$5:$E$207) | D13: =SUMIF('库存流水'!$B$5:$B$207,A13,'库存流水'!$F$5:$F$207) | E13: =SUMIF('库存流水'!$B$5:$B$207,A13,'库存流水'!$G$5:$G$207) | F13: =SUMIFS('库存流水'!$H$5:$H$207,'库存流水'!$B$5:$B$207,A13,'库存流水'!$L$5:$L$207,1) | G13: =B13-D13-E13-F13 | H13: =SUMIF('销售流水'!$C$5:$C$203,A13,'销售流水'!$F$5:$F$203) | I13: =IF(D13=0,0,H13/D13) | J13: =SUMIFS('报损折价'!$F$5:$F$79,'报损折价'!$C$5:$C$79,A13,'报损折价'!$J$5:$J$79,"是") | K13: =SUMIF('冷链温控'!$A$5:$A$144,A13,'冷链温控'!$H$5:$H$144) | L13: =MINIFS('质检抽检'!$E$5:$E$144,'质检抽检'!$B$5:$B$144,A13) | M13: =SUMIF('渠道动销'!$C$5:$C$94,A13,'渠道动销'!$F$5:$F$94)
A14: NY-KW-2508-010 | B14: =SUMIF('采购批次'!$A$5:$A$32,A14,'采购批次'!$G$5:$G$32) | C14: =SUMIF('库存流水'!$B$5:$B$207,A14,'库存流水'!$E$5:$E$207) | D14: =SUMIF('库存流水'!$B$5:$B$207,A14,'库存流水'!$F$5:$F$207) | E14: =SUMIF('库存流水'!$B$5:$B$207,A14,'库存流水'!$G$5:$G$207) | F14: =SUMIFS('库存流水'!$H$5:$H$207,'库存流水'!$B$5:$B$207,A14,'库存流水'!$L$5:$L$207,1) | G14: =B14-D14-E14-F14 | H14: =SUMIF('销售流水'!$C$5:$C$203,A14,'销售流水'!$F$5:$F$203) | I14: =IF(D14=0,0,H14/D14) | J14: =SUMIFS('报损折价'!$F$5:$F$79,'报损折价'!$C$5:$C$79,A14,'报损折价'!$J$5:$J$79,"是") | K14: =SUMIF('冷链温控'!$A$5:$A$144,A14,'冷链温控'!$H$5:$H$144) | L14: =MINIFS('质检抽检'!$E$5:$E$144,'质检抽检'!$B$5:$B$144,A14) | M14: =SUMIF('渠道动销'!$C$5:$C$94,A14,'渠道动销'!$F$5:$F$94)
A15: NY-KW-2508-011 | B15: =SUMIF('采购批次'!$A$5:$A$32,A15,'采购批次'!$G$5:$G$32) | C15: =SUMIF('库存流水'!$B$5:$B$207,A15,'库存流水'!$E$5:$E$207) | D15: =SUMIF('库存流水'!$B$5:$B$207,A15,'库存流水'!$F$5:$F$207) | E15: =SUMIF('库存流水'!$B$5:$B$207,A15,'库存流水'!$G$5:$G$207) | F15: =SUMIFS('库存流水'!$H$5:$H$207,'库存流水'!$B$5:$B$207,A15,'库存流水'!$L$5:$L$207,1) | G15: =B15-D15-E15-F15 | H15: =SUMIF('销售流水'!$C$5:$C$203,A15,'销售流水'!$F$5:$F$203) | I15: =IF(D15=0,0,H15/D15) | J15: =SUMIFS('报损折价'!$F$5:$F$79,'报损折价'!$C$5:$C$79,A15,'报损折价'!$J$5:$J$79,"是") | K15: =SUMIF('冷链温控'!$A$5:$A$144,A15,'冷链温控'!$H$5:$H$144) | L15: =MINIFS('质检抽检'!$E$5:$E$144,'质检抽检'!$B$5:$B$144,A15) | M15: =SUMIF('渠道动销'!$C$5:$C$94,A15,'渠道动销'!$F$5:$F$94)
A16: NY-KW-2508-012 | B16: =SUMIF('采购批次'!$A$5:$A$32,A16,'采购批次'!$G$5:$G$32) | C16: =SUMIF('库存流水'!$B$5:$B$207,A16,'库存流水'!$E$5:$E$207) | D16: =SUMIF('库存流水'!$B$5:$B$207,A16,'库存流水'!$F$5:$F$207) | E16: =SUMIF('库存流水'!$B$5:$B$207,A16,'库存流水'!$G$5:$G$207) | F16: =SUMIFS('库存流水'!$H$5:$H$207,'库存流水'!$B$5:$B$207,A16,'库存流水'!$L$5:$L$207,1) | G16: =B16-D16-E16-F16 | H16: =SUMIF('销售流水'!$C$5:$C$203,A16,'销售流水'!$F$5:$F$203) | I16: =IF(D16=0,0,H16/D16) | J16: =SUMIFS('报损折价'!$F$5:$F$79,'报损折价'!$C$5:$C$79,A16,'报损折价'!$J$5:$J$79,"是") | K16: =SUMIF('冷链温控'!$A$5:$A$144,A16,'冷链温控'!$H$5:$H$144) | L16: =MINIFS('质检抽检'!$E$5:$E$144,'质检抽检'!$B$5:$B$144,A16) | M16: =SUMIF('渠道动销'!$C$5:$C$94,A16,'渠道动销'!$F$5:$F$94)
... A32: NY-KW-2508-028 | B32: =SUMIF('采购批次'!$A$5:$A$32,A32,'采购批次'!$G$5:$G$32) | C32: =SUMIF('库存流水'!$B$5:$B$207,A32,'库存流水'!$E$5:$E$207) | D32: =SUMIF('库存流水'!$B$5:$B$207,A32,'库存流水'!$F$5:$F$207) | E32: =SUMIF('库存流水'!$B$5:$B$207,A32,'库存流水'!$G$5:$G$207) | F32: =SUMIFS('库存流水'!$H$5:$H$207,'库存流水'!$B$5:$B$207,A32,'库存流水'!$L$5:$L$207,1) | G32: =B32-D32-E32-F32 | H32: =SUMIF('销售流水'!$C$5:$C$203,A32,'销售流水'!$F$5:$F$203) | I32: =IF(D32=0,0,H32/D32) | J32: =SUMIFS('报损折价'!$F$5:$F$79,'报损折价'!$C$5:$C$79,A32,'报损折价'!$J$5:$J$79,"是") | K32: =SUMIF('冷链温控'!$A$5:$A$144,A32,'冷链温控'!$H$5:$H$144) | L32: =MINIFS('质检抽检'!$E$5:$E$144,'质检抽检'!$B$5:$B$144,A32) | M32: =SUMIF('渠道动销'!$C$5:$C$94,A32,'渠道动销'!$F$5:$F$94)

Sheet 经营基线
A1: 经营基线
A2: 所有指标均由业务原始表或批次对账公式汇总；覆盖范围不同的表分别呈现，不作无依据合并。
A4: 指标 | B4: 数值 | C4: 单位 | D4: 口径说明 | E4: 来源
A5: 采购批次数 | B5: =COUNTA('采购批次'!$A$5:$A$32) | C5: 批 | D5: 去重后采购批次 | E5: 采购批次
A6: 采购到货量 | B6: =SUM('采购批次'!$G$5:$G$32) | C6: kg | D6: 采购台账到货量合计 | E6: 采购批次
A7: 采购金额 | B7: =SUM('采购批次'!$I$5:$I$32) | C7: 元 | D7: 采购台账金额合计 | E7: 采购批次
A8: 加权采购单价 | B8: =B7/B6 | C8: 元/kg | D8: 采购金额/到货量 | E8: 采购批次
A9: 库存出库量 | B9: =SUM('库存流水'!$F$5:$F$207) | C9: kg | D9: 库存流水出库量合计 | E9: 库存流水
A10: 库存报损量 | B10: =SUM('库存流水'!$G$5:$G$207) | C10: kg | D10: 库存流水报损量合计 | E10: 库存流水
A11: 末笔期末库存 | B11: =SUM('批次对账'!$F$5:$F$32) | C11: kg | D11: 各批次末笔期末库存合计 | E11: 批次对账
A12: 库存平衡差异 | B12: =SUM('批次对账'!$G$5:$G$32) | C12: kg | D12: 采购到货-出库-报损-末笔库存 | E12: 批次对账
A13: 成熟相关问题量 | B13: =SUMIFS('报损折价'!$F$5:$F$79,'报损折价'!$J$5:$J$79,"是") | C13: kg | D13: 问题记录中标记为成熟相关 | E13: 报损折价
A14: 成熟相关损失 | B14: =SUMIFS('报损折价'!$I$5:$I$79,'报损折价'!$J$5:$J$79,"是") | C14: 元 | D14: 估计损失字段合计 | E14: 报损折价
A15: 销售量 | B15: =SUM('销售流水'!$F$5:$F$203) | C15: kg | D15: 销售记录覆盖量，不等于全部库存出库 | E15: 销售流水
A16: 销售收入 | B16: =SUM('销售流水'!$J$5:$J$203) | C16: 元 | D16: 销售收入合计 | E16: 销售流水
A17: 加权平均售价 | B17: =B16/B15 | C17: 元/kg | D17: 销售收入/销售量 | E17: 销售流水
A18: 折价销售量 | B18: =SUM('销售流水'!$H$5:$H$203) | C18: kg | D18: 折价销售kg合计 | E18: 销售流水
A19: 折价销售占比 | B19: =B18/B15 | C19: % | D19: 折价销售量/销售量 | E19: 销售流水
A20: 退货量 | B20: =SUM('销售流水'!$K$5:$K$203) | C20: kg | D20: 退货kg合计 | E20: 销售流水
A21: 退货率 | B21: =B20/B15 | C21: % | D21: 退货量/销售量 | E21: 销售流水
A22: 客诉件数 | B22: =SUM('销售流水'!$L$5:$L$203) | C22: 件 | D22: 客诉件数合计 | E22: 销售流水
A23: 冷链超温小时 | B23: =SUM('冷链温控'!$H$5:$H$144) | C23: 小时 | D23: 逐环节超温小时合计 | E23: 冷链温控
A24: 断链记录数 | B24: =COUNTIF('冷链温控'!$J$5:$J$144,"是") | C24: 条 | D24: 是否断链=是 | E24: 冷链温控
A25: 质检抽检果数 | B25: =SUM('质检抽检'!$D$5:$D$144) | C25: 个 | D25: 抽检果数合计 | E25: 质检抽检
A26: 不建议销售记录 | B26: =COUNTIF('质检抽检'!$H$5:$H$144,"不建议销售") | C26: 条 | D26: 销售建议字段 | E26: 质检抽检
A27: 渠道到货量 | B27: =SUM('渠道动销'!$F$5:$F$94) | C27: kg | D27: 渠道表覆盖量 | E27: 渠道动销
A28: 渠道加权偏软率 | B28: =SUMPRODUCT('渠道动销'!$F$5:$F$94,'渠道动销'!$H$5:$H$94)/B27 | C28: % | D28: 按到货量加权 | E28: 渠道动销
A29: 渠道加权折价率 | B29: =SUMPRODUCT('渠道动销'!$F$5:$F$94,'渠道动销'!$I$5:$I$94)/B27 | C29: % | D29: 按到货量加权 | E29: 渠道动销
A30: 平均售完天数 | B30: =AVERAGE('渠道动销'!$J$5:$J$94) | C30: 天 | D30: 渠道表简单平均 | E30: 渠道动销
A31: 平均变动处理成本 | B31: =SUMIFS('处理成本'!$D$5:$D$28,'处理成本'!$C$5:$C$28,"元/kg果")/3 | C31: 元/kg | D31: 三个月各变动成本项目之和的月均值 | E31: 处理成本
A32: 平均每批固定成本 | B32: =SUMIFS('处理成本'!$D$5:$D$28,'处理成本'!$C$5:$C$28,"元/批")/3 | C32: 元/批 | D32: 三个月每批费用合计的月均值 | E32: 处理成本
A33: 平均月培训成本 | B33: =AVERAGEIFS('处理成本'!$D$5:$D$28,'处理成本'!$C$5:$C$28,"元/月") | C33: 元/月 | D33: 三个月培训费用平均 | E33: 处理成本

Sheet 情景测算
A1: GA₃处理供应链应用情景测算
A2: 黄色为可调整假设；历史基线来自“经营基线”。测算仅用于筛选验证价值，不代表已实现收益或商业施用许可。
A4: 基线参数 | B4: 数值 | C4: 单位 | D4: 来源/说明
A5: 评估期处理量 | B5: ='经营基线'!B6 | C5: kg | D5: 采购到货量，作为全量情景规模
A6: 评估期批次数 | B6: ='经营基线'!B5 | C6: 批 | D6: 采购批次数
A7: 评估期月数 | B7: 3 | C7: 月 | D7: 2025-08至2025-10的计划假设
A8: 平均变动成本 | B8: ='经营基线'!B31 | C8: 元/kg | D8: 三个月处理药剂、现场人工、设备折旧月均合计
A9: 平均每批固定成本 | B9: ='经营基线'!B32 | C9: 元/批 | D9: 残留检测、品质复检、追溯和废液处理月均合计
A10: 平均月培训成本 | B10: ='经营基线'!B33 | C10: 元/月 | D10: 培训费用月均值
A11: 成熟相关损失基线 | B11: ='经营基线'!B14 | C11: 元 | D11: 成熟相关问题记录的估计损失
A12: 折价销售量基线 | B12: ='经营基线'!B18 | C12: kg | D12: 销售流水折价销售量
A13: 退货量基线 | B13: ='经营基线'!B20 | C13: kg | D13: 销售流水退货量
A14: 加权平均售价 | B14: ='经营基线'!B17 | C14: 元/kg（13元/斤=26元/kg） | D14: 销售收入/销售量；已按猕猴桃市场价13元/斤折算 | E14: 销售流水（按13元/斤更新）
A16: 情景假设与结果 | B16: 保守 | C16: 中性 | D16: 乐观
A17: 成熟相关损失减少率 | B17: 0.1 | C17: 0.2 | D17: 0.3 | E17: %
A18: 折价销售量减少率 | B18: 0.05 | C18: 0.1 | D18: 0.15 | E18: %
A19: 折价价差 | B19: 1.5 | C19: 2 | D19: 2.5 | E19: 元/kg；需在试点中实测
A20: 退货减少率 | B20: 0.05 | C20: 0.1 | D20: 0.15 | E20: %
A21: 退货损失率 | B21: 0.7 | C21: 0.8 | D21: 0.9 | E21: %；退货量对应损失价值比例
A22: 可售窗口延长 | B22: 2 | C22: 4 | D22: 6 | E22: 天；待冷链试验验证
A24: 测算结果 | B24: 保守 | C24: 中性 | D24: 乐观 | F24: 情景 | G24: 净价值(元)
A25: 减损收益 | B25: =$B$11*B$17 | C25: =$B$11*C$17 | D25: =$B$11*D$17 | F25: 保守 | G25: =B33
A26: 折价回收价值 | B26: =$B$12*B$18*B$19 | C26: =$B$12*C$18*C$19 | D26: =$B$12*D$18*D$19 | F26: 中性 | G26: =C33
A27: 退货回收价值 | B27: =$B$13*B$20*$B$14*B$21 | C27: =$B$13*C$20*$B$14*C$21 | D27: =$B$13*D$20*$B$14*D$21 | F27: 乐观 | G27: =D33
A28: 收益合计 | B28: =SUM(B25:B27) | C28: =SUM(C25:C27) | D28: =SUM(D25:D27)
A29: 变动处理成本 | B29: =$B$5*$B$8 | C29: =$B$5*$B$8 | D29: =$B$5*$B$8
A30: 每批固定成本 | B30: =$B$6*$B$9 | C30: =$B$6*$B$9 | D30: =$B$6*$B$9
A31: 培训成本 | B31: =$B$7*$B$10 | C31: =$B$7*$B$10 | D31: =$B$7*$B$10
A32: 成本合计 | B32: =SUM(B29:B31) | C32: =SUM(C29:C31) | D32: =SUM(D29:D31)
A33: 净价值 | B33: =B28-B32 | C33: =C28-C32 | D33: =D28-D32
A34: 收益/成本 | B34: =IF(B32=0,0,B28/B32) | C34: =IF(C32=0,0,C28/C32) | D34: =IF(D32=0,0,D28/D32)
A35: 结论 | B35: =IF(B33>0,"具备经济验证空间","成本高于当前可量化收益") | C35: =IF(C33>0,"具备经济验证空间","成本高于当前可量化收益") | D35: =IF(D33>0,"具备经济验证空间","成本高于当前可量化收益")
A37: 试点预算 | B37: 数值 | C37: 单位 | D37: 说明
A38: 试点处理量 | B38: 30000 | C38: kg | D38: 规划假设，可调整
A39: 试点批次数 | B39: 3 | C39: 批 | D39: 规划假设，可调整
A40: 试点月数 | B40: 1 | C40: 月 | D40: 规划假设，可调整
A41: 预计试点成本 | B41: =B38*$B$8+B39*$B$9+B40*$B$10 | C41: 元 | D41: 不含设备改造停线和注册申报成本

Sheet 证据台账
A1: 证据台账
A2: 科研论文已按DOI注册元数据复核题名和年份；标准与法规按官方入口记录现行状态和适用边界；检索日期用于标记本次公开资料核验时点。
A4: 编号 | B4: 资料类型 | C4: 年份 | D4: 题名或文件名 | E4: 标识或标准号 | F4: 来源入口 | G4: 检索日期 | H4: 本项目用途 | I4: 主要边界 | J4: 状态
A5: E01 | B5: 科研论文 | C5: 1989 | D5: Changes in the softening and composition of kiwifruit affected by maturity at harvest and postharvest treatments | E5: 10.1002/jsfa.2740490404 | F5: https://doi.org/10.1002/jsfa.2740490404 | G5: 2026-08-18 | H5: 采收成熟度与批次外推 | I5: 研究对象和处理条件不同 | J5: 有效
A6: E02 | B6: 科研论文 | C6: 1992 | D6: Cell Wall Dissolution in Ripening Kiwifruit | E6: 10.1104/pp.98.1.71 | F6: https://doi.org/10.1104/pp.98.1.71 | G6: 2026-08-18 | H6: 细胞壁软化机制背景 | I6: 本项目未测果胶或细胞壁酶 | J6: 有效
A7: E03 | B7: 科研论文 | C7: 2011 | D7: Dissecting the role of climacteric ethylene in kiwifruit ripening using an ACC oxidase knockdown line | E7: 10.1093/jxb/err063 | F7: https://doi.org/10.1093/jxb/err063 | G7: 2026-08-18 | H7: 乙烯参与成熟后段 | I7: 转基因材料不能证明GA3直接靶点 | J7: 有效
A8: E04 | B8: 科研论文 | C8: 2012 | D8: Low-temperature-modulated fruit ripening is independent of ethylene in Sanuki Gold kiwifruit | E8: 10.1093/jxb/err324 | F8: https://doi.org/10.1093/jxb/err324 | G8: 2026-08-18 | H8: 低温乙烯非依赖路径 | I8: 品种和温度不同 | J8: 有效
A9: E05 | B9: 科研论文 | C9: 2016 | D9: Characterization of Starch Degradation Related Genes in Postharvest Kiwifruit | E9: 10.3390/ijms17122112 | F9: https://doi.org/10.3390/ijms17122112 | G9: 2026-08-18 | H9: 淀粉降解候选机制 | I9: 不能替代本项目基因或酶活测定 | J9: 有效
A10: E06 | B10: 科研论文 | C10: 2017 | D10: Untargeted multi-platform analysis of the metabolome and the non-starch polysaccharides of kiwifruit during postharvest ripening | E10: 10.1016/j.postharvbio.2016.10.011 | F10: https://doi.org/10.1016/j.postharvbio.2016.10.011 | G10: 2026-08-18 | H10: 多指标成熟背景 | I10: 本项目不含代谢组验证 | J10: 有效
A11: E07 | B11: 科研论文 | C11: 2018 | D11: Transcriptome Analysis Identifies a Zinc Finger Protein Regulating Starch Degradation in Kiwifruit | E11: 10.1104/pp.18.00427 | F11: https://doi.org/10.1104/pp.18.00427 | G11: 2026-08-18 | H11: 淀粉降解转录调控背景 | I11: 本项目不含转录数据 | J11: 有效
A12: E08 | B12: 科研论文 | C12: 2019 | D12: Low Temperature Storage Stimulates Fruit Softening and Sugar Accumulation Without Ethylene and Aroma Volatile Production in Kiwifruit | E12: 10.3389/fpls.2019.00888 | F12: https://doi.org/10.3389/fpls.2019.00888 | G12: 2026-08-18 | H12: 低温糖积累与香气边界 | I12: 20℃结果不能直接代表冷链 | J12: 有效
A13: E09 | B13: 科研论文 | C13: 2020 | D13: Fruit From Two Kiwifruit Genotypes With Contrasting Softening Rates Show Differences in the Cell Wall Domains | E13: 10.3389/fpls.2020.00964 | F13: https://doi.org/10.3389/fpls.2020.00964 | G13: 2026-08-18 | H13: 品种外推风险 | I13: 不同基因型需独立验证 | J13: 有效
A14: E10 | B14: 科研论文 | C14: 2021 | D14: Quality of Hayward Kiwifruit in Prolonged Cold Storage as Affected by the Stage of Maturity at Harvest | E14: 10.3390/horticulturae7100358 | F14: https://doi.org/10.3390/horticulturae7100358 | G14: 2026-08-18 | H14: 采收成熟度与冷藏 | I14: 海沃德和其他品种不可直接互推 | J14: 有效
A15: E11 | B15: 科研论文 | C15: 2023 | D15: Targeted multi-platform metabolome analysis and enzyme activity analysis of kiwifruit during postharvest ripening | E15: 10.3389/fpls.2023.1120166 | F15: https://doi.org/10.3389/fpls.2023.1120166 | G15: 2026-08-18 | H15: 机制验证层级 | I15: 本项目仅有六项生理指标 | J15: 有效
... A27: E23 | B27: 境外法规 | C27: 2014 | D27: Commission Regulation EU No 588/2014 concerning maximum residue levels | E27: CELEX 32014R0588 | F27: European Commission | G27: 2026-08-18 | H27: 欧盟MRL历史背景 | I27: 需另行核对当前出口市场要求 | J27: 历史背景

Sheet 决策门槛
A1: 决策门槛
A2: 阶段门用于组织验证与决策，不是商业施用指令；任何进入商品化的结论均受G3合规闭环约束。
A4: 阶段门 | B4: 核心问题 | C4: 必要证据 | D4: 继续条件 | E4: 保持/补充条件 | F4: 停止条件 | G4: 责任接口
A5: G0 数据可解释 | B5: 现有小试是否具备可解释的设计与数据身份 | C5: 补齐品种、采收成熟度、处理产品/浓度/方法、温湿度、取样方式和重复独立性；锁定原始数据版本 | D5: 设计信息完整且数据主键、单位、重复和异常处理规则可追溯 | E5: 部分设计信息可补证但尚未闭环 | F5: 关键试验条件无法追溯或数据版本无法确认 | G5: 研发/质量
A6: G1 独立复现 | B6: 成熟延缓效应是否跨批次稳定 | C6: 至少两个独立采收批次；预先指定主要终点、最小有意义差异和统计方案 | D6: 主要终点方向一致且效应区间达到预设标准，无明显基线失衡 | E6: 效应方向一致但不确定性仍大，追加批次 | F6: 效应反转、仅单指标驱动或严重基线失衡 | G6: 研发/统计
A7: G2 冷链转化 | B7: 常温结果能否转化为冷链和到货表现 | C7: 温度×处理交互试验；硬度、TSS、酸、腐烂、失重、感官、运输耐受和可售窗口 | D7: 冷链条件下仍获得可操作的窗口增益且无质量代价 | E7: 窗口增益有限或存在温度依赖，调整工艺 | F7: 冷链下无效或风味、腐烂、运输风险恶化 | G7: 冷链/质量/研发
A8: G3 合规闭环 | B8: 具体产品与用途是否具备合法使用路径 | C8: 有效登记证、核准标签、使用范围与方法、残留与检测方案、属地监管确认 | D8: 全部资料经法规与质量部门书面确认 | E8: 产品或用途尚待核查，仅限受控研发 | F8: 无法获得合法使用依据或风险不可接受 | G8: 法规/质量
A9: G4 运营可控 | B9: 处理能否稳定嵌入分选、仓储和追溯流程 | C9: SOP、人员防护、设备能力、批次追溯、废液处置、处理均一性和异常处置记录 | D9: 关键过程参数受控且批次记录完整 | E9: 局部偏差可通过SOP和设备优化纠正 | F9: 处理均一性或追溯无法保证 | G9: 运营/仓储/质量
A10: G5 经济验证 | B10: 收益能否覆盖完整增量成本且不转移风险 | C10: 试点真实处理量、可售窗口、报损折价、退货客诉、价格差、变动和固定成本 | D10: 经实际试点复算后达到企业预设收益门槛，且投诉与退货不恶化 | E10: 净价值接近门槛，需缩小范围或优化成本 | F10: 成本持续高于可验证收益或渠道风险上升 | G10: 品类经营/财务/质量

Sheet 补充增强说明
A1: 模块 | B1: 补充内容 | C1: 用于强化的rubric方向 | D1: 是否改变既有公式链
A2: 反向业务风险 | B2: 将偏硬客诉、适食成熟比例和渠道验收作为GA₃延熟的反向风险监控项，防止把过熟损失转移为偏硬未熟损失。 | C2: 表型图与经营数据联动；受控试点停止条件 | D2: 否
A3: 统计解释边界 | B3: 均值、样本标准差、Welch检验和多重比较只支持方向性判断；p值不得替代效应轨迹、样本限制和独立批次复现。 | C3: 统计边界；反单一p值；独立复现 | D3: 否
A4: 冷链外推边界 | B4: 20℃小试不能直接外推到0–5℃冷链和门店货架；需关注低温乙烯非依赖软化路径和温度×处理交互。 | C4: 科研证据分层；冷链转化；外推限制 | D4: 否
A5: 经营价值来源 | B5: 成熟相关减损、折价回收、退货回收和可售窗口延长均为待验证收益池；三情景净价值为负时不得全量推广。 | C5: 情景净价值；收益池/成本池；未验证收益 | D5: 否
A6: 合规沟通边界 | B6: 登记证、核准标签、残留控制和属地监管核验完成前，不得形成商业施用方法、销售承诺或对外宣传口径。 | C6: 商品化合规；对外宣传边界 | D6: 否
A7: 交付洁净度 | B7: 最终交付物不得出现模型名称、/app或本地路径、制作说明、占位符或与业务无关文字。 | C7: 交付洁净度；可直接客户交付 | D7: 否
